pyefa/__init__.py
pyefa/client.py
pyefa/data_classes.py
pyefa/exceptions.py
pyefa/helpers.py
pyefa/requests/__init__.py
pyefa/requests/req.py
pyefa/requests/req_departures.py
pyefa/requests/req_stop_finder.py
pyefa/requests/req_system_info.py
pyefa/requests/req_trips.py
pyefa-0.0.3.dist-info/LICENSE
pyefa-0.0.3.dist-info/METADATA
pyefa-0.0.3.dist-info/WHEEL
pyefa-0.0.3.dist-info/top_level.txt
pyefa-0.0.3.dist-info/RECORD
