Metadata-Version: 2.1
Name: pyefa
Version: 0.0.3
Summary: Python API for EFA(Elektronische Fahrplanauskunft) async requests
Author-email: Alex Jung <jungdevelop@gmail.com>
License: MIT License
Project-URL: Homepage, https://github.com/alex-jung/pyefa
Project-URL: Documentation, https://github.com/alex-jung/pyefa
Project-URL: Repository, https://github.com/alex-jung/pyefa
Project-URL: Issues, https://github.com/alex-jung/pyefa/issues
Keywords: efa,vgn,gtfs,public transport,traffic
Requires-Python: >=3.11
License-File: LICENSE
Requires-Dist: aiohttp==3.11.7
Requires-Dist: voluptuous==0.15.2
Requires-Dist: tzdata==2024.2
Provides-Extra: tests
Requires-Dist: coverage>=5.0.3; extra == "tests"
Requires-Dist: pytest-cov; extra == "tests"
Requires-Dist: pytest; extra == "tests"
Requires-Dist: pytest-benchmark[histogram]>=3.2.1; extra == "tests"
